chess_library_exporter.py
ChessComLibraryExporter-0.7.2.dist-info/LICENSE
ChessComLibraryExporter-0.7.2.dist-info/METADATA
ChessComLibraryExporter-0.7.2.dist-info/WHEEL
ChessComLibraryExporter-0.7.2.dist-info/entry_points.txt
ChessComLibraryExporter-0.7.2.dist-info/top_level.txt
ChessComLibraryExporter-0.7.2.dist-info/RECORD
