Metadata-Version: 2.1
Name: ChessComLibraryExporter
Version: 0.7.2
Summary: Download your whole Chess.com Library (chess.com/library)
Home-page: https://github.com/manuelpepe/ChessComLibraryExporter
Author: Manuel Pepe
Author-email: manuelpepe-dev@outlook.com.ar
License: MIT
License-File: LICENSE
Requires-Dist: selenium
Requires-Dist: webdriver-manager
Requires-Dist: pathvalidate
Requires-Dist: python-dotenv
